Counters/codd_asyn/codd_asyn.srcs/sources_1/new/asyn.v
`timescale 1ns / 1ps
//////////////////////////////////////////////////////////////////////////////////
// Company: 
// Engineer: 
// 
// Create Date: 07/06/2023 09:03:00 PM
// Design Name: 
// Module Name: asyn
// Project Name: 
// Target Devices: 
// Tool Versions: 
// Description: 
// 
// Dependencies: 
// 
// Revision:
// Revision 0.01 - File Created
// Additional Comments:
// 
//////////////////////////////////////////////////////////////////////////////////


module dff (
  input wire clk,
  input wire d,
  input wire rstn,
  output reg q,
  output reg qn
);

  always @(posedge clk or negedge rstn) begin
    if (~rstn)
      q <= 0;
    else
      q <= d;
    qn <= ~q;
  end

endmodule


module ripple (
  input wire clk,
  input wire rstn,
  output wire [3:0] out
);

  wire q0, q1, q2, q3;
  wire qn0, qn1, qn2, qn3;

  dff dff0 (.clk(clk), .d(qn0), .rstn(rstn), .q(q0), .qn(qn0));
  dff dff1 (.clk(clk), .d(qn1), .rstn(rstn), .q(q1), .qn(qn1));
  dff dff2 (.clk(clk), .d(qn2), .rstn(rstn), .q(q2), .qn(qn2));
  dff dff3 (.clk(clk), .d(qn3), .rstn(rstn), .q(q3), .qn(qn3));

  assign out = {q3, q2, q1, q0};

endmodule

Counters/codd_asyn/codd_asyn.srcs/sim_1/new/asyn_tb.v

//////////////////////////////////////////////////////////////////////////////////
// Company: 
// Engineer: 
// 
// Create Date: 07/06/2023 09:03:54 PM
// Design Name: 
// Module Name: asyn_tb
// Project Name: 
// Target Devices: 
// Tool Versions: 
// Description: 
// 
// Dependencies: 
// 
// Revision:
// Revision 0.01 - File Created
// Additional Comments:
// 
//////////////////////////////////////////////////////////////////////////////////

module tb_ripple;

  reg clk;
  reg rstn;

  wire [3:0] out;

  ripple counter (
    .clk(clk),
    .rstn(rstn),
    .out(out)
  );

  initial begin
    $dumpfile("counter.vcd");
    $dumpvars(0, tb_ripple);

    rstn = 0;
    clk = 0;
    #20 rstn = 1;
  end

  always #5 clk = ~clk;
  
endmodule

Counters/codd_asyn/codd_asyn.sim/sim_1/behav/xsim/counter.vcd
$date
   Thu Jul  6 21:26:42 2023
$end
$version
  2023.1
$end
$timescale
  1ps
$end
$scope module tb_ripple $end
$var reg 1 ! clk $end
$var reg 1 " rstn $end
$var wire 4 # out [3:0] $end
$scope module counter $end
$var wire 1 $ clk $end
$var wire 1 % rstn $end
$var wire 4 # out [3:0] $end
$var wire 1 & q0 $end
$var wire 1 ' q1 $end
$var wire 1 ( q2 $end
$var wire 1 ) q3 $end
$var wire 1 * qn0 $end
$var wire 1 + qn1 $end
$var wire 1 , qn2 $end
$var wire 1 - qn3 $end
$scope module dff0 $end
$var wire 1 $ clk $end
$var wire 1 * d $end
$var wire 1 % rstn $end
$var reg 1 . q $end
$var reg 1 / qn $end
$upscope $end
$scope module dff1 $end
$var wire 1 $ clk $end
$var wire 1 + d $end
$var wire 1 % rstn $end
$var reg 1 0 q $end
$var reg 1 1 qn $end
$upscope $end
$scope module dff2 $end
$var wire 1 $ clk $end
$var wire 1 , d $end
$var wire 1 % rstn $end
$var reg 1 2 q $end
$var reg 1 3 qn $end
$upscope $end
$scope module dff3 $end
$var wire 1 $ clk $end
$var wire 1 - d $end
$var wire 1 % rstn $end
$var reg 1 4 q $end
$var reg 1 5 qn $end
$upscope $end
$upscope $end
$upscope $end
$enddefinitions $end
#0
$dumpvars
0!
0"
b0 #
0$
0%
0&
0'
0(
0)
x*
x+
x,
x-
0.
x/
00
x1
02
x3
04
x5
$end
#5000
1!
1$
1*
1+
1,
1-
1/
11
13
15
#10000
0!
0$
#15000
1!
1$
#20000
0!
1"
0$
1%
#25000
1!
b1111 #
1$
1&
1'
1(
1)
1.
10
12
14
#30000
0!
0$
#35000
1!
1$
0*
0+
0,
0-
0/
01
03
05
#40000
0!
0$
#45000
1!
b0 #
1$
0&
0'
0(
0)
0.
00
02
04
#50000
0!
0$
#55000
1!
1$
1*
1+
1,
1-
1/
11
13
15
#60000
0!
0$
#65000
1!
b1111 #
1$
1&
1'
1(
1)
1.
10
12
14
#70000
0!
0$
#75000
1!
1$
0*
0+
0,
0-
0/
01
03
05
#80000
0!
0$
#85000
1!
b0 #
1$
0&
0'
0(
0)
0.
00
02
04
#90000
0!
0$
#95000
1!
1$
1*
1+
1,
1-
1/
11
13
15
#100000
0!
0$
#105000
1!
b1111 #
1$
1&
1'
1(
1)
1.
10
12
14
#110000
0!
0$
#115000
1!
1$
0*
0+
0,
0-
0/
01
03
05
#120000
0!
0$
#125000
1!
b0 #
1$
0&
0'
0(
0)
0.
00
02
04
#130000
0!
0$
#135000
1!
1$
1*
1+
1,
1-
1/
11
13
15
#140000
0!
0$
#145000
1!
b1111 #
1$
1&
1'
1(
1)
1.
10
12
14
#150000
0!
0$
#155000
1!
1$
0*
0+
0,
0-
0/
01
03
05
#160000
0!
0$
#165000
1!
b0 #
1$
0&
0'
0(
0)
0.
00
02
04
#170000
0!
0$
#175000
1!
1$
1*
1+
1,
1-
1/
11
13
15
#180000
0!
0$
#185000
1!
b1111 #
1$
1&
1'
1(
1)
1.
10
12
14
#190000
0!
0$
#195000
1!
1$
0*
0+
0,
0-
0/
01
03
05
#200000
0!
0$
#205000
1!
b0 #
1$
0&
0'
0(
0)
0.
00
02
04
#210000
0!
0$
#215000
1!
1$
1*
1+
1,
1-
1/
11
13
15
#220000
0!
0$
#225000
1!
b1111 #
1$
1&
1'
1(
1)
1.
10
12
14
#230000
0!
0$
#235000
1!
1$
0*
0+
0,
0-
0/
01
03
05
#240000
0!
0$
#245000
1!
b0 #
1$
0&
0'
0(
0)
0.
00
02
04
#250000
0!
0$
#255000
1!
1$
1*
1+
1,
1-
1/
11
13
15
#260000
0!
0$
#265000
1!
b1111 #
1$
1&
1'
1(
1)
1.
10
12
14
#270000
0!
0$
#275000
1!
1$
0*
0+
0,
0-
0/
01
03
05
#280000
0!
0$
#285000
1!
b0 #
1$
0&
0'
0(
0)
0.
00
02
04
#290000
0!
0$
#295000
1!
1$
1*
1+
1,
1-
1/
11
13
15
#300000
0!
0$
#305000
1!
b1111 #
1$
1&
1'
1(
1)
1.
10
12
14
#310000
0!
0$
#315000
1!
1$
0*
0+
0,
0-
0/
01
03
05
#320000
0!
0$
#325000
1!
b0 #
1$
0&
0'
0(
0)
0.
00
02
04
#330000
0!
0$
#335000
1!
1$
1*
1+
1,
1-
1/
11
13
15
#340000
0!
0$
#345000
1!
b1111 #
1$
1&
1'
1(
1)
1.
10
12
14
#350000
0!
0$
#355000
1!
1$
0*
0+
0,
0-
0/
01
03
05
#360000
0!
0$
#365000
1!
b0 #
1$
0&
0'
0(
0)
0.
00
02
04
#370000
0!
0$
#375000
1!
1$
1*
1+
1,
1-
1/
11
13
15
#380000
0!
0$
#385000
1!
b1111 #
1$
1&
1'
1(
1)
1.
10
12
14
#390000
0!
0$
#395000
1!
1$
0*
0+
0,
0-
0/
01
03
05
#400000
0!
0$
#405000
1!
b0 #
1$
0&
0'
0(
0)
0.
00
02
04
#410000
0!
0$
#415000
1!
1$
1*
1+
1,
1-
1/
11
13
15
#420000
0!
0$
#425000
1!
b1111 #
1$
1&
1'
1(
1)
1.
10
12
14
#430000
0!
0$
#435000
1!
1$
0*
0+
0,
0-
0/
01
03
05
#440000
0!
0$
#445000
1!
b0 #
1$
0&
0'
0(
0)
0.
00
02
04
#450000
0!
0$
#455000
1!
1$
1*
1+
1,
1-
1/
11
13
15
#460000
0!
0$
#465000
1!
b1111 #
1$
1&
1'
1(
1)
1.
10
12
14
#470000
0!
0$
#475000
1!
1$
0*
0+
0,
0-
0/
01
03
05
#480000
0!
0$
#485000
1!
b0 #
1$
0&
0'
0(
0)
0.
00
02
04
#490000
0!
0$
#495000
1!
1$
1*
1+
1,
1-
1/
11
13
15
#500000
0!
0$
#505000
1!
b1111 #
1$
1&
1'
1(
1)
1.
10
12
14
#510000
0!
0$
#515000
1!
1$
0*
0+
0,
0-
0/
01
03
05
#520000
0!
0$
#525000
1!
b0 #
1$
0&
0'
0(
0)
0.
00
02
04
#530000
0!
0$
#535000
1!
1$
1*
1+
1,
1-
1/
11
13
15
#540000
0!
0$
#545000
1!
b1111 #
1$
1&
1'
1(
1)
1.
10
12
14
#550000
0!
0$
#555000
1!
1$
0*
0+
0,
0-
0/
01
03
05
#560000
0!
0$
#565000
1!
b0 #
1$
0&
0'
0(
0)
0.
00
02
04
#570000
0!
0$
#575000
1!
1$
1*
1+
1,
1-
1/
11
13
15
#580000
0!
0$
#585000
1!
b1111 #
1$
1&
1'
1(
1)
1.
10
12
14
#590000
0!
0$
#595000
1!
1$
0*
0+
0,
0-
0/
01
03
05
#600000
0!
0$
#605000
1!
b0 #
1$
0&
0'
0(
0)
0.
00
02
04
#610000
0!
0$
#615000
1!
1$
1*
1+
1,
1-
1/
11
13
15
#620000
0!
0$
#625000
1!
b1111 #
1$
1&
1'
1(
1)
1.
10
12
14
#630000
0!
0$
#635000
1!
1$
0*
0+
0,
0-
0/
01
03
05
#640000
0!
0$
#645000
1!
b0 #
1$
0&
0'
0(
0)
0.
00
02
04
#650000
0!
0$
#655000
1!
1$
1*
1+
1,
1-
1/
11
13
15
#660000
0!
0$
#665000
1!
b1111 #
1$
1&
1'
1(
1)
1.
10
12
14
#670000
0!
0$
#675000
1!
1$
0*
0+
0,
0-
0/
01
03
05
#680000
0!
0$
#685000
1!
b0 #
1$
0&
0'
0(
0)
0.
00
02
04
#690000
0!
0$
#695000
1!
1$
1*
1+
1,
1-
1/
11
13
15
#700000
0!
0$
#705000
1!
b1111 #
1$
1&
1'
1(
1)
1.
10
12
14
#710000
0!
0$
#715000
1!
1$
0*
0+
0,
0-
0/
01
03
05
#720000
0!
0$
#725000
1!
b0 #
1$
0&
0'
0(
0)
0.
00
02
04
#730000
0!
0$
#735000
1!
1$
1*
1+
1,
1-
1/
11
13
15
#740000
0!
0$
#745000
1!
b1111 #
1$
1&
1'
1(
1)
1.
10
12
14
#750000
0!
0$
#755000
1!
1$
0*
0+
0,
0-
0/
01
03
05
#760000
0!
0$
#765000
1!
b0 #
1$
0&
0'
0(
0)
0.
00
02
04
#770000
0!
0$
#775000
1!
1$
1*
1+
1,
1-
1/
11
13
15
#780000
0!
0$
#785000
1!
b1111 #
1$
1&
1'
1(
1)
1.
10
12
14
#790000
0!
0$
#795000
1!
1$
0*
0+
0,
0-
0/
01
03
05
#800000
0!
0$
#805000
1!
b0 #
1$
0&
0'
0(
0)
0.
00
02
04
#810000
0!
0$
#815000
1!
1$
1*
1+
1,
1-
1/
11
13
15
#820000
0!
0$
#825000
1!
b1111 #
1$
1&
1'
1(
1)
1.
10
12
14
#830000
0!
0$
#835000
1!
1$
0*
0+
0,
0-
0/
01
03
05
#840000
0!
0$
#845000
1!
b0 #
1$
0&
0'
0(
0)
0.
00
02
04
#850000
0!
0$
#855000
1!
1$
1*
1+
1,
1-
1/
11
13
15
#860000
0!
0$
#865000
1!
b1111 #
1$
1&
1'
1(
1)
1.
10
12
14
#870000
0!
0$
#875000
1!
1$
0*
0+
0,
0-
0/
01
03
05
#880000
0!
0$
#885000
1!
b0 #
1$
0&
0'
0(
0)
0.
00
02
04
#890000
0!
0$
#895000
1!
1$
1*
1+
1,
1-
1/
11
13
15
#900000
0!
0$
#905000
1!
b1111 #
1$
1&
1'
1(
1)
1.
10
12
14
#910000
0!
0$
#915000
1!
1$
0*
0+
0,
0-
0/
01
03
05
#920000
0!
0$
#925000
1!
b0 #
1$
0&
0'
0(
0)
0.
00
02
04
#930000
0!
0$
#935000
1!
1$
1*
1+
1,
1-
1/
11
13
15
#940000
0!
0$
#945000
1!
b1111 #
1$
1&
1'
1(
1)
1.
10
12
14
#950000
0!
0$
#955000
1!
1$
0*
0+
0,
0-
0/
01
03
05
#960000
0!
0$
#965000
1!
b0 #
1$
0&
0'
0(
0)
0.
00
02
04
#970000
0!
0$
#975000
1!
1$
1*
1+
1,
1-
1/
11
13
15
#980000
0!
0$
#985000
1!
b1111 #
1$
1&
1'
1(
1)
1.
10
12
14
#990000
0!
0$
#995000
1!
1$
0*
0+
0,
0-
0/
01
03
05
